Topsis/__init__.py
Topsis/__main__.py
Topsis_Aadishri_102083030-1.0.0.dist-info/LICENSE
Topsis_Aadishri_102083030-1.0.0.dist-info/METADATA
Topsis_Aadishri_102083030-1.0.0.dist-info/WHEEL
Topsis_Aadishri_102083030-1.0.0.dist-info/entry_points.txt
Topsis_Aadishri_102083030-1.0.0.dist-info/top_level.txt
Topsis_Aadishri_102083030-1.0.0.dist-info/RECORD
