Metadata-Version: 2.1
Name: Topsis-Aadishri-102083030
Version: 1.0.0
Summary: Calculates TOPSIS on the given dataset!
Home-page: https://github.com/aadishri17/Topsis-Aadishri-102083030
Author: Aadishri Soni
Author-email: aadishrisoni123@gmail.com
License: MIT
Platform: UNKNOWN
Classifier: License :: OSI Approved :: MIT License
Classifier: Programming Language :: Python :: 3.8
Classifier: Programming Language :: Python :: 3.9
Classifier: Programming Language :: Python :: 3.10
License-File: LICENSE
Requires-Dist: pandas
